nci_cidc_cli/__init__.py
nci_cidc_cli/api.py
nci_cidc_cli/auth.py
nci_cidc_cli/cache.py
nci_cidc_cli/cli.py
nci_cidc_cli/config.py
nci_cidc_cli/consent.py
nci_cidc_cli/gcloud.py
nci_cidc_cli/upload.py
nci_cidc_cli/dbedit/__init__.py
nci_cidc_cli/dbedit/cli.py
nci_cidc_cli/dbedit/config.py
nci_cidc_cli/dbedit/core.py
nci_cidc_cli/dbedit/list.py
nci_cidc_cli/dbedit/remove.py
nci_cidc_cli-1.1.4.dist-info/licenses/LICENSE
tests/__init__.py
tests/conftest.py
tests/test_api.py
tests/test_auth.py
tests/test_cache.py
tests/test_cli.py
tests/test_upload.py
tests/util.py
tests/dbedit/__init__.py
tests/dbedit/constants.py
tests/dbedit/test_core.py
tests/dbedit/test_list.py
tests/dbedit/test_remove.py
nci_cidc_cli-1.1.4.dist-info/METADATA
nci_cidc_cli-1.1.4.dist-info/WHEEL
nci_cidc_cli-1.1.4.dist-info/entry_points.txt
nci_cidc_cli-1.1.4.dist-info/top_level.txt
nci_cidc_cli-1.1.4.dist-info/RECORD
