Metadata-Version: 2.4
Name: nci_cidc_cli
Version: 1.1.4
Summary: A command-line interface for interacting with the NCI CIDC.
Requires-Python: >=3.6
License-File: LICENSE
Requires-Dist: click>=8.2.1
Requires-Dist: cloud-sql-python-connector[pg8000]>=1.18.4
Requires-Dist: pandas>2.3.1
Requires-Dist: python-dotenv>=1.1.1
Requires-Dist: pyperclip>=1.9.0
Requires-Dist: requests>=2.32.5
Requires-Dist: sqlalchemy>=2.0.43
Requires-Dist: numpy>=2.3.2
Dynamic: description
Dynamic: description-content-type
Dynamic: license-file
Dynamic: requires-dist
Dynamic: requires-python
Dynamic: summary
